flat_ray/__init__.py
flat_ray/analyzer.py
flat_ray/cli.py
flat_ray-0.1.0.dist-info/licenses/LICENSE
flat_ray-0.1.0.dist-info/METADATA
flat_ray-0.1.0.dist-info/WHEEL
flat_ray-0.1.0.dist-info/entry_points.txt
flat_ray-0.1.0.dist-info/top_level.txt
flat_ray-0.1.0.dist-info/RECORD
