Metadata-Version: 2.4
Name: flat-ray
Version: 0.1.0
Summary: A CLI tool that scans malformed or well-formed XML/HTML files and produces a flat, hierarchical summary of tags, attributes, and values. Basic usage: Structural analysis before data transformation or corpora integration into larger pipelines.
Author: Lucas Terriel
License: MIT License
Requires-Python: >=3.8
License-File: LICENSE
Requires-Dist: sloppy-xml
Requires-Dist: rich
Requires-Dist: tqdm
Requires-Dist: joblib
Requires-Dist: termcolor
Dynamic: license-file
